ezKit/__init__.py
ezKit/__zabbix.py
ezKit/asyncdatabase.py
ezKit/bandwagon.py
ezKit/cipher.py
ezKit/database.py
ezKit/errorcode.py
ezKit/fastapix.py
ezKit/http.py
ezKit/linux.py
ezKit/markdown_to_html.template
ezKit/redix.py
ezKit/sendemail.py
ezKit/stock.py
ezKit/utils.py
ezkit-2.0.36.dist-info/licenses/LICENSE
ezkit-2.0.36.dist-info/METADATA
ezkit-2.0.36.dist-info/WHEEL
ezkit-2.0.36.dist-info/top_level.txt
ezkit-2.0.36.dist-info/RECORD
