Metadata-Version: 2.4
Name: ezKit
Version: 2.0.36
Summary: Easy Kit
Author: septvean
Author-email: septvean@gmail.com
Requires-Python: >=3.12
License-File: LICENSE
Requires-Dist: loguru>=0.7
Dynamic: author
Dynamic: author-email
Dynamic: license-file
Dynamic: requires-dist
Dynamic: requires-python
Dynamic: summary
